django_runas-0.1.3.dist-info/DESCRIPTION.rst
django_runas-0.1.3.dist-info/METADATA
django_runas-0.1.3.dist-info/RECORD
django_runas-0.1.3.dist-info/WHEEL
django_runas-0.1.3.dist-info/metadata.json
django_runas-0.1.3.dist-info/top_level.txt
runas/__init__.py
runas/middleware.py
runas/urls.py
runas/views.py
runas/static/css/runas.css
runas/templates/admin/auth/user/change_form.html
runas/templates/includes/runas/banner.html
runas/templatetags/__init__.py
runas/templatetags/runas_tags.py
